demo/__init__.py
demo/arrows.py
demo/background.py
demo/bat.py
demo/clear.py
demo/example2player.py
demo/follow.py
demo/gate.py
demo/gateway.py
demo/house.py
demo/pagoda.py
demo/shapes.py
demo/snowball.py
demo/village.py
demo/walls.py
mciwb/__init__.py
mciwb/__main__.py
mciwb/_version.py
mciwb/backup.py
mciwb/copier.py
mciwb/imports.py
mciwb/iwb.py
mciwb/logging.py
mciwb/monitor.py
mciwb/nbt.py
mciwb/player.py
mciwb/server.py
mciwb/signs.py
mciwb/switch.py
mciwb/threads.py
mciwb/utils.py
mciwb/wall.py
mciwb-0.9.1.dist-info/LICENSE
mciwb-0.9.1.dist-info/METADATA
mciwb-0.9.1.dist-info/WHEEL
mciwb-0.9.1.dist-info/entry_points.txt
mciwb-0.9.1.dist-info/top_level.txt
mciwb-0.9.1.dist-info/RECORD
