Metadata-Version: 2.1
Name: mciwb
Version: 0.9.1
Summary: Minecraft Interactive world builder
Author-email: Giles Knap <gilesknap@gmail.com>
License: Apache License
Project-URL: GitHub, https://github.com/gilesknap/mciwb
Classifier: Development Status :: 3 - Alpha
Classifier: License :: OSI Approved :: Apache Software License
Classifier: Programming Language :: Python :: 3.10
Classifier: Programming Language :: Python :: 3.11
Classifier: Programming Language :: Python :: 3.12
Requires-Python: >=3.10
License-File: LICENSE
Requires-Dist: numpy
Requires-Dist: typer
Requires-Dist: mcwb ==0.3.0b2
Requires-Dist: ipython
Requires-Dist: docker >=6
Provides-Extra: dev
Requires-Dist: copier ; extra == 'dev'
Requires-Dist: myst-parser ; extra == 'dev'
Requires-Dist: pipdeptree ; extra == 'dev'
Requires-Dist: pre-commit ; extra == 'dev'
Requires-Dist: pydata-sphinx-theme >=0.12 ; extra == 'dev'
Requires-Dist: pyright ; extra == 'dev'
Requires-Dist: pytest ; extra == 'dev'
Requires-Dist: pytest-cov ; extra == 'dev'
Requires-Dist: ruff ; extra == 'dev'
Requires-Dist: sphinx-autobuild ; extra == 'dev'
Requires-Dist: sphinx-copybutton ; extra == 'dev'
Requires-Dist: sphinx-design ; extra == 'dev'
Requires-Dist: tox-direct ; extra == 'dev'
Requires-Dist: types-mock ; extra == 'dev'
